perftrackerlib/__init__.py
perftrackerlib/client.py
perftrackerlib/helpers/__init__.py
perftrackerlib/helpers/decorators.py
perftrackerlib/helpers/html.py
perftrackerlib/helpers/largelogfile.py
perftrackerlib/helpers/ptshell.py
perftrackerlib/helpers/tee.py
perftrackerlib/helpers/textparser.py
perftrackerlib/helpers/texttable.py
perftrackerlib/helpers/timehelpers.py
perftrackerlib/helpers/timeline.py
perftrackerlib/helpers/timeparser.py
perftrackerlib/helpers/timeline/formatendefault.js
perftrackerlib/helpers/timeline/jsapi.js
perftrackerlib/helpers/timeline/table.css
perftrackerlib/helpers/timeline/timeline-locales.js
perftrackerlib/helpers/timeline/timeline-min.js
perftrackerlib/helpers/timeline/timeline-theme.css
perftrackerlib/helpers/timeline/timeline.css
perftrackerlib/helpers/timeline/timeline.js
perftrackerlib/helpers/timeline/udate.js
perftrackerlib-0.1.8.data/scripts/pt-artifact-ctl.py
perftrackerlib-0.1.8.data/scripts/pt-suite-uploader.py
perftrackerlib-0.1.8.dist-info/LICENSE
perftrackerlib-0.1.8.dist-info/METADATA
perftrackerlib-0.1.8.dist-info/WHEEL
perftrackerlib-0.1.8.dist-info/top_level.txt
perftrackerlib-0.1.8.dist-info/RECORD
