Metadata-Version: 2.1
Name: perftrackerlib
Version: 0.1.8
Summary: Python package with perftracker client, tools, tests and libraries
Home-page: http://www.perftracker.org
Author: perfguru87
Author-email: perfguru87@gmail.com
License: MIT License
Keywords: performance tests tools selenium webdriver perftracker client
Platform: UNKNOWN
Classifier: Development Status :: 3 - Alpha
Classifier: Intended Audience :: Developers
Classifier: Topic :: Software Development :: Testing
Classifier: License :: OSI Approved :: MIT License
Classifier: Programming Language :: Python :: 2.6
Classifier: Programming Language :: Python :: 2.7
Classifier: Programming Language :: Python :: 3
Classifier: Programming Language :: Python :: 3.3
Classifier: Programming Language :: Python :: 3.4
Classifier: Programming Language :: Python :: 3.5
Requires-Dist: requests
Requires-Dist: python-dateutil
Requires-Dist: citizenshell
Provides-Extra: test
Requires-Dist: pycodestyle ; extra == 'test'
Requires-Dist: coverage ; extra == 'test'
